README.md
setup.py
jsontokens/__init__.py
jsontokens/key_loading.py
jsontokens/token_signer.py
jsontokens/token_verifier.py
jsontokens/utils.py
jsontokens.egg-info/PKG-INFO
jsontokens.egg-info/SOURCES.txt
jsontokens.egg-info/dependency_links.txt
jsontokens.egg-info/not-zip-safe
jsontokens.egg-info/requires.txt
jsontokens.egg-info/top_level.txt