Metadata-Version: 1.1
Name: jsontokens
Version: 0.0.5
Summary: JSON Web Token Python Library
Home-page: https://github.com/blockstack/jsontokens-py
Author: Blockstack Developers
Author-email: hello@onename.com
License: MIT
Keywords: json web token sign verify encode decode signature
Platform: UNKNOWN
Classifier: Intended Audience :: Developers
Classifier: License :: OSI Approved :: MIT License
Classifier: Operating System :: OS Independent
Classifier: Programming Language :: Python
Classifier: Topic :: Internet
Classifier: Topic :: Security :: Cryptography
Classifier: Topic :: Software Development :: Libraries :: Python Modules
